<?xml version="1.0" encoding="utf-8" ?>
<dwsync>
<file name="0b5ffdecf29b8fefc9db176869d4bd93ca0f7c2f.file.login.tpl.php" server="192.168.1.100" local="131236421818416729" remote="131225278800000000" Dst="1" />
<file name="0fda2e09855b4bd3cd33daeb1774a8455d109d8e.file.index.tpl.php" server="192.168.1.100" local="131236421819061814" remote="131225278800000000" Dst="1" />
<file name="0808848dd4da517d1076b02b55a50538ecc90273.file.serverview.tpl.php" server="192.168.1.100" local="131236421821737150" remote="131232523800000000" Dst="1" />
<file name="1dd191d2099a346ae132fe0820b1f1428cf63249.file.showupdate.tpl.php" server="192.168.1.100" local="131236421821867173" remote="131225278800000000" Dst="1" />
<file name="2cff7105c10b7648381596c03feacbd9cab669ea.file.interactive.tpl.php" server="192.168.1.100" local="131236421824949692" remote="131227390800000000" Dst="1" />
<file name="10d73f7ae36874d071f1793142f4685d6d79be60.file.mainbar.tpl.php" server="192.168.1.100" local="131236421826514849" remote="131232523200000000" Dst="1" />
<file name="2f596c95eaa5a60bd1037c6d0de629ce12626df6.file.server.tpl.php" server="192.168.1.100" local="131236421827549990" remote="131232523200000000" Dst="1" />
<file name="37f16e30add7173f80893f178f009bdb65d19dc2.file.index.tpl.php" server="192.168.1.100" local="131236421828180068" remote="131232523200000000" Dst="1" />
<file name="3b79cbccf450c7c94591b0b3ff076479b7a372f1.file.mainbar.tpl.php" server="192.168.1.100" local="131236421829455232" remote="131115300600000000" Dst="1" />
<file name="47c9515d72849058ce9c9072180754d7460e4419.file.head.tpl.php" server="192.168.1.100" local="131236421829720257" remote="131225278800000000" Dst="1" />
<file name="6f627d82ced6c357ab24df9d07b31d86f27fb39f.file.head.tpl.php" server="192.168.1.100" local="131236421830000300" remote="131232523200000000" Dst="1" />
<file name="73e9cf217703403064dd06d5e9420febec657b73.file.login.tpl.php" server="192.168.1.100" local="131236421830405353" remote="131115300600000000" Dst="1" />
<file name="90fd44d6b66a54ef95f7246155f21f45b783983c.file.server.tpl.php" server="192.168.1.100" local="131236421831420481" remote="131225280000000000" Dst="1" />
<file name="933c13d105df235b977707c4febc99fc347bb8e9.file.clients.tpl.php" server="192.168.1.100" local="131236421832560626" remote="131225301600000000" Dst="1" />
<file name="ab847af03924765e1f53e1b7546453dec64bb95c.file.index.tpl.php" server="192.168.1.100" local="131236421833255717" remote="131115322800000000" Dst="1" />
<file name="b3a93a609cb705f8c63ed3151060f5465af695c7.file.head.tpl.php" server="192.168.1.100" local="131236421833520747" remote="131115300600000000" Dst="1" />
<file name="bac462ab9d7e0a2cbfb16e5401c7c8bd75a0855c.file.servertraffic.tpl.php" server="192.168.1.100" local="131236421834370855" remote="131225304000000000" Dst="1" />
<file name="bb839cc9349f41fbfb3923fb4b73517e17bdbf28.file.showupdate.tpl.php" server="192.168.1.100" local="131236421834530876" remote="131232523200000000" Dst="1" />
<file name="c834596e23b0f6ab4fae8228f21e0da469b2255e.file.showupdate.tpl.php" server="192.168.1.100" local="131236421834645882" remote="131115300600000000" Dst="1" />
<file name="ca78738000eb81b0463d6633f546d12a47e8571b.file.iserverbackup.tpl.php" server="192.168.1.100" local="131236421835981061" remote="131227391400000000" Dst="1" />
<file name="e03bda40c4a144184231b03b805fdd7c19f22467.file.logview.tpl.php" server="192.168.1.100" local="131236421836546131" remote="131227391400000000" Dst="1" />
<file name="df3055c2e0ad678c5f62619f9b9fc8ea6f2b882f.file.serverview.tpl.php" server="192.168.1.100" local="131236421839246478" remote="131225301000000000" Dst="1" />
<file name="f00063cbf2fb6e0dea1a07e02d168ce9e1bea79a.file.mainbar.tpl.php" server="192.168.1.100" local="131236421840456630" remote="131225278800000000" Dst="1" />
<file name="fb64d93c29fbdf4ea106ae7907c2696749cb063f.file.login.tpl.php" server="192.168.1.100" local="131236421840856680" remote="131232523200000000" Dst="1" />
<file name="fd2457e4a09c47e7dff28ea8471923f2979a464a.file.counter.tpl.php" server="192.168.1.100" local="131236421844856769" remote="131225302200000000" Dst="1" />
</dwsync>