<?xml version="1.0" encoding="utf-8" ?>
<dwsync>
<file name="geonyx.css" server="192.168.1.100" local="131236421316171600" remote="131231446200000000" Dst="1" />
<file name="github.css" server="192.168.1.100" local="131236421316231608" remote="131231446200000000" Dst="1" />
<file name="kimono.css" server="192.168.1.100" local="131236421316306618" remote="131231446200000000" Dst="1" />
<file name="luminous.css" server="192.168.1.100" local="131236421316336612" remote="131231446200000000" Dst="1" />
<file name="luminous.scss" server="192.168.1.100" local="131236421316376618" remote="131231446200000000" Dst="1" />
<file name="luminous_dark.css" server="192.168.1.100" local="131236421316436626" remote="131231446200000000" Dst="1" />
<file name="luminous_light.css" server="192.168.1.100" local="131236421316466644" remote="131231446200000000" Dst="1" />
<file name="luminous_print.css" server="192.168.1.100" local="131236421316496646" remote="131231446200000000" Dst="1" />
<file name="paradise.css" server="192.168.1.100" local="131236421316556656" remote="131231446200000000" Dst="1" />
<file name="soft.css" server="192.168.1.100" local="131236421316591655" remote="131231446200000000" Dst="1" />
<file name="zenophilia.css" server="192.168.1.100" local="131236421316631660" remote="131231446200000000" Dst="1" />
</dwsync>